[
  {
    "message": "引き戸を静かに開け。"
  },
  {
    "message": "横山サンが廊下の様子を窺う。"
  },
  {
    "name": "横山",
    "message": "…今です。"
  },
  {
    "message": "雪菜ちゃんが前。"
  },
  {
    "message": "その後に奥さんが続く。"
  },
  {
    "message": "もちろん先頭に立ってるのは横山サンで。"
  },
  {
    "message": "麻呂はみんなの背後を守った。"
  },
  {
    "message": "照明の灯る廊下をヒタヒタと歩き。"
  },
  {
    "message": "何回か角を曲がった後。"
  },
  {
    "message": "あり得ない状況に愕然とし。"
  },
  {
    "message": "暫し４人は開いた口が塞がらない。"
  },
  {
    "name": "咲美",
    "message": "何だ、これ。"
  },
  {
    "name": "横山",
    "message": "…ここを真っ直ぐ行けば、部屋へ辿り着くのに。"
  },
  {
    "name": "彦麻呂",
    "message": "どうやら楽しんでるみたいですねぇ。"
  },
  {
    "name": "雪菜",
    "message": "こ、こんなの普通じゃありません。"
  },
  {
    "name": "彦麻呂",
    "message": "…。"
  },
  {
    "name": "彦麻呂",
    "message": "…誰か近づいてきます。"
  },
  {
    "message": "足音は背後から。"
  },
  {
    "message": "麻呂は奇襲攻撃に備え。"
  },
  {
    "message": "今度は油断する事なく身構える。"
  },
  {
    "name": "彦麻呂",
    "message": "来ますよぉ。"
  },
  {
    "message": "ブタ男３が現れた！"
  },
  {
    "message": "ブタ男４が現れた！"
  },
  {
    "name": "ブタ男３",
    "message": "…。"
  },
  {
    "message": "ブタ男３はじっと咲美を見てる。"
  },
  {
    "name": "ブタ男４",
    "message": "…。"
  },
  {
    "message": "ブタ男４もじっと咲美を見てる。"
  },
  {
    "name": "咲美",
    "message": "な、なに？"
  },
  {
    "message": "誰が攻撃しますか？"
  },
  {
    "message": "麻呂"
  },
  {
    "message": "横山"
  },
  {
    "message": "咲美"
  },
  {
    "message": "雪菜"
  },
  {
    "message": "通常攻撃"
  },
  {
    "message": "選び直す"
  },
  {
    "message": "どちらのブタを攻撃しますか？"
  },
  {
    "message": "ブタ男３"
  },
  {
    "message": "ブタ男４"
  },
  {
    "message": "選び直す"
  },
  {
    "message": "ばきっ！"
  },
  {
    "name": "ブタ男３",
    "message": "ぐはっ！"
  },
  {
    "message": "麻呂はブタ男３に公家パンチを繰り出した！"
  },
  {
    "message": "ブタ男３に２５のダメージを与えた！"
  },
  {
    "message": "ブタ男３の体力は残り"
  },
  {
    "message": "だ。"
  },
  {
    "message": "ブタ男３は戦闘不能になった！"
  },
  {
    "message": "ばきっ！"
  },
  {
    "name": "ブタ男４",
    "message": "ぐはっ！"
  },
  {
    "message": "麻呂はブタ男４に蹴鞠キックをお見舞いした！"
  },
  {
    "message": "ブタ男４に３０のダメージを与えた！"
  },
  {
    "message": "ブタ男４の体力は残り"
  },
  {
    "message": "だ。"
  },
  {
    "message": "ブタ男４は戦闘不能になった！"
  },
  {
    "message": "通常攻撃"
  },
  {
    "message": "選び直す"
  },
  {
    "message": "どちらのブタを攻撃しますか？"
  },
  {
    "message": "ブタ男３"
  },
  {
    "message": "ブタ男４"
  },
  {
    "message": "選び直す"
  },
  {
    "message": "どかっ！"
  },
  {
    "name": "ブタ男３",
    "message": "いてっ！"
  },
  {
    "message": "横山はブタ男３を殴った！"
  },
  {
    "message": "ブタ男３に１５のダメージを与えた！"
  },
  {
    "message": "ブタ男３の体力は残り"
  },
  {
    "message": "だ。"
  },
  {
    "message": "ブタ男３は戦闘不能になった！"
  },
  {
    "message": "どかっ！"
  },
  {
    "name": "ブタ男４",
    "message": "いてっ！"
  },
  {
    "message": "横山はブタ男４を殴った！"
  },
  {
    "message": "ブタ男４に１５のダメージを与えた！"
  },
  {
    "message": "ブタ男４の体力は残り"
  },
  {
    "message": "だ。"
  },
  {
    "message": "ブタ男４は戦闘不能になった！"
  },
  {
    "message": "通常攻撃"
  },
  {
    "message": "選び直す"
  },
  {
    "message": "どちらのブタを攻撃しますか？"
  },
  {
    "message": "ブタ男３"
  },
  {
    "message": "ブタ男４"
  },
  {
    "message": "選び直す"
  },
  {
    "message": "ばきっ！"
  },
  {
    "name": "ブタ男３",
    "message": "ぐはっ！"
  },
  {
    "message": "咲美はブタ男３を殴った！"
  },
  {
    "message": "ブタ男３に２５のダメージを与えた！"
  },
  {
    "message": "ブタ男３の体力は残り"
  },
  {
    "message": "だ。"
  },
  {
    "message": "ブタ男３は戦闘不能になった！"
  },
  {
    "message": "ばきっ！"
  },
  {
    "name": "ブタ男４",
    "message": "ぐはっ！"
  },
  {
    "message": "咲美はブタ男４を殴った！"
  },
  {
    "message": "ブタ男４に２５のダメージを与えた！"
  },
  {
    "message": "ブタ男４の体力は残り"
  },
  {
    "message": "だ。"
  },
  {
    "message": "ブタ男４は戦闘不能になった！"
  },
  {
    "message": "通常攻撃"
  },
  {
    "message": "選び直す"
  },
  {
    "message": "どちらのブタを攻撃しますか？"
  },
  {
    "message": "ブタ男３"
  },
  {
    "message": "ブタ男４"
  },
  {
    "message": "選び直す"
  },
  {
    "name": "雪菜",
    "message": "え、えいっ。"
  },
  {
    "message": "ぱっちん。"
  },
  {
    "name": "ブタ男３",
    "message": "はぁ？"
  },
  {
    "message": "雪菜はブタ男３をひっ叩いた。"
  },
  {
    "message": "でも５のダメージしか与えられない。"
  },
  {
    "message": "ブタ男３の体力は残り"
  },
  {
    "message": "だ。"
  },
  {
    "message": "ブタ男３は戦闘不能になった！"
  },
  {
    "name": "雪菜",
    "message": "え、えいっ。"
  },
  {
    "message": "ぱっちん。"
  },
  {
    "name": "ブタ男４",
    "message": "ふふっ。"
  },
  {
    "message": "雪菜はブタ男４をひっ叩いた。"
  },
  {
    "message": "でも５のダメージしか与えられない。"
  },
  {
    "message": "ブタ男４の体力は残り"
  },
  {
    "message": "だ。"
  },
  {
    "message": "ブタ男４は戦闘不能になった！"
  },
  {
    "name": "横山",
    "message": "か、勝ちましたぁ。"
  },
  {
    "name": "咲美",
    "message": "はあっ…はあっ…。"
  },
  {
    "name": "彦麻呂",
    "message": "っ、大丈夫ですかぁ？"
  },
  {
    "name": "咲美",
    "message": "な、何とか…。"
  },
  {
    "name": "彦麻呂",
    "message": "よくぞセクハラ攻撃に堪えましたぁ。"
  },
  {
    "name": "彦麻呂",
    "message": "っ、みんなボロボロですぅ。"
  },
  {
    "name": "咲美",
    "message": "っ、好き勝手に触りやがってぇ…。"
  },
  {
    "name": "珍念",
    "message": "…素晴らしいチームワークですね。"
  },
  {
    "name": "咲美",
    "message": "う、うわ…。"
  },
  {
    "name": "珍念",
    "message": "けっこうやるじゃないですか。"
  },
  {
    "name": "咲美",
    "message": "こ、この番頭さんも悪いヤツ？"
  },
  {
    "name": "彦麻呂",
    "message": "っ、一気にやっつけてしまいましょう。"
  },
  {
    "name": "横山",
    "message": "…いや。"
  },
  {
    "message": "横山サンは腕を伸ばし。"
  },
  {
    "message": "挑みかかろうとする麻呂を止める。"
  },
  {
    "name": "横山",
    "message": "ここは私にまかせて下さい。"
  },
  {
    "message": "そう言った横山サンさん。"
  },
  {
    "message": "一歩前に進み出て。"
  },
  {
    "message": "珍念の真正面に凛として立った。"
  },
  {
    "name": "横山",
    "message": "どうも。"
  },
  {
    "message": "まずはペコリと会釈。"
  },
  {
    "message": "珍念の眉はピクリと動いたが。"
  },
  {
    "message": "それに対する返礼は無しだ。"
  },
  {
    "message": "でも横山サンは動じない。"
  },
  {
    "message": "戸惑う事なくじっと相手を見据え。"
  },
  {
    "message": "口元には友好的な笑みさえ浮かべてる。"
  },
  {
    "name": "横山",
    "message": "アナタはマトモな方のようです。"
  },
  {
    "name": "珍念",
    "message": "…どうしてそう思うんですか？"
  },
  {
    "name": "横山",
    "message": "言葉遣いにも品があります。"
  },
  {
    "name": "珍念",
    "message": "…下品なのは嫌いですからね。"
  },
  {
    "name": "横山",
    "message": "暴力も否定派なのでは？"
  },
  {
    "name": "珍念",
    "message": "腕力が知恵と経験に勝てるワケもない。"
  },
  {
    "name": "横山",
    "message": "さすがですね。"
  },
  {
    "name": "珍念",
    "message": "褒めたって何もあげませんよ。"
  },
  {
    "name": "横山",
    "message": "…カブリ物で顔も隠してませんし。"
  },
  {
    "name": "珍念",
    "message": "公募した連中と一緒にしないで下さい。"
  },
  {
    "name": "横山",
    "message": "つまりご自分のしてる事に、責任を持っていらっしゃる。"
  },
  {
    "name": "珍念",
    "message": "そんなの当然です。"
  },
  {
    "name": "横山",
    "message": "地位が高い方とお見受けしましたが。"
  },
  {
    "name": "珍念",
    "message": "…。"
  },
  {
    "name": "横山",
    "message": "もしかして今件の代表者ですか？"
  },
  {
    "name": "珍念",
    "message": "…幹部とだけ申しておきましょう。"
  },
  {
    "name": "横山",
    "message": "いったい何の幹部なんですかね。"
  },
  {
    "name": "珍念",
    "message": "問われて答えるほど、馬鹿じゃありません。"
  },
  {
    "name": "横山",
    "message": "そこを何とか教えて下さいよ。"
  },
  {
    "name": "珍念",
    "message": "無理ですね。"
  },
  {
    "name": "横山",
    "message": "どなたかに断りが必要ですか？"
  },
  {
    "name": "珍念",
    "message": "…。"
  },
  {
    "name": "横山",
    "message": "ご自分の意志ではどーにもならない？"
  },
  {
    "name": "珍念",
    "message": "誰がそんな事を言いました？"
  },
  {
    "name": "横山",
    "message": "なら、是非。"
  },
  {
    "name": "珍念",
    "message": "我々はクラブを経営してます。"
  },
  {
    "name": "横山",
    "message": "何のクラブでしょうか？"
  },
  {
    "name": "珍念",
    "message": "残念ながらここまでです。"
  },
  {
    "name": "横山",
    "message": "ほう…。"
  },
  {
    "name": "珍念",
    "message": "…なんで薄笑いなんですか？"
  },
  {
    "name": "横山",
    "message": "大した幹部サンだなって。"
  },
  {
    "name": "珍念",
    "message": "…。"
  },
  {
    "name": "横山",
    "message": "どうやら買い被っていたようです。"
  },
  {
    "name": "珍念",
    "message": "人妻専門の秘密クラブですよ。"
  },
  {
    "name": "横山",
    "message": "…さすがです。"
  },
  {
    "name": "珍念",
    "message": "本気で私が答えられないとでも？"
  },
  {
    "name": "横山",
    "message": "幹部サンを見くびってました。"
  },
  {
    "name": "珍念",
    "message": "私の事を舐めないで頂きたい。"
  },
  {
    "name": "横山",
    "message": "…秘密クラブですから会員制ですよね？"
  },
  {
    "name": "珍念",
    "message": "言うまでもありません。"
  },
  {
    "name": "横山",
    "message": "その会員さん達はどんな恩恵を？"
  },
  {
    "name": "珍念",
    "message": "そこまで説明する必要がどこに？"
  },
  {
    "name": "横山",
    "message": "ほほう…。"
  },
  {
    "name": "珍念",
    "message": "…また薄笑いですか。"
  },
  {
    "name": "横山",
    "message": "あなたの限界が見えましたので。"
  },
  {
    "name": "珍念",
    "message": "限界？"
  },
  {
    "name": "横山",
    "message": "背伸びするのもここまでか、と。"
  },
  {
    "name": "珍念",
    "message": "もしかして私の事を馬鹿にしてます？"
  },
  {
    "name": "横山",
    "message": "まさか。"
  },
  {
    "name": "珍念",
    "message": "っ、ならその薄ら笑いをやめろ。"
  },
  {
    "name": "横山",
    "message": "微笑みは友好の証だと認識してます。"
  },
  {
    "name": "珍念",
    "message": "…その類の笑みじゃない。"
  },
  {
    "name": "横山",
    "message": "受け取る側の問題だと思いますけど。"
  },
  {
    "name": "珍念",
    "message": "…。"
  },
  {
    "name": "横山",
    "message": "何かコンプレックスをお持ちですか？"
  },
  {
    "name": "珍念",
    "message": "っ、くだらない話はもうおしまいです。男性二人は今すぐこの旅館から退去し、ここで起きた一切の事を口外しないように…。"
  },
  {
    "name": "横山",
    "message": "女性達二人を見捨てろと？"
  },
  {
    "name": "珍念",
    "message": "見捨てるのではなく預けるんですよ。"
  },
  {
    "name": "横山",
    "message": "お金はいくら頂けるんですかね？"
  },
  {
    "name": "雪菜",
    "message": "ぇ…。"
  },
  {
    "name": "咲美",
    "message": "ちょっ…。"
  },
  {
    "name": "彦麻呂",
    "message": "…。"
  },
  {
    "message": "今度は麻呂が腕を伸ばし。"
  },
  {
    "message": "前に出ようとする奥さんを制す。"
  },
  {
    "name": "横山",
    "message": "そういう事は金額次第だと思いますが。"
  },
  {
    "name": "珍念",
    "message": "それこそ私の一存じゃ決められません。"
  },
  {
    "name": "横山",
    "message": "地位の高い幹部サンなのに？"
  },
  {
    "name": "珍念",
    "message": "お金の話は別です。"
  },
  {
    "name": "横山",
    "message": "お金の話だからこそ、幹部サンなのでは？"
  },
  {
    "name": "珍念",
    "message": "見解の相違ですね。"
  },
  {
    "name": "横山",
    "message": "実は幹部じゃないとか？"
  },
  {
    "name": "珍念",
    "message": "し、失敬な。"
  },
  {
    "name": "横山",
    "message": "本当に幹部？"
  },
  {
    "name": "珍念",
    "message": "そう言ったでしょ？"
  },
  {
    "name": "横山",
    "message": "へえ…。"
  },
  {
    "name": "珍念",
    "message": "っ、その薄笑いは本当に失礼ですよ。"
  },
  {
    "name": "横山",
    "message": "…やはりただの透明人間でしたかぁ。"
  },
  {
    "name": "珍念",
    "message": "や、やはりって何だよ。"
  },
  {
    "name": "横山",
    "message": "ご自分のしてる事に責任の欠片もない、空気と同じ重さの透明人間です。"
  },
  {
    "name": "珍念",
    "message": "ぅ…。"
  },
  {
    "name": "横山",
    "message": "つまりアンタは…。"
  },
  {
    "message": "横山サンは更に一歩前へ出て。"
  },
  {
    "message": "鼻がつきそうなくらい顔を近づけた。"
  },
  {
    "name": "横山",
    "message": "カブリ物の連中と同じ、下劣な操り人形だっ！"
  },
  {
    "name": "珍念",
    "message": "…。"
  },
  {
    "name": "横山",
    "message": "本当は自分一人じゃ何もできない、虎の威を借りてるチキン野郎だっ！"
  },
  {
    "name": "珍念",
    "message": "ぐはっ！"
  },
  {
    "message": "プライドの高い珍念に痛恨の一撃！"
  },
  {
    "message": "珍念は１００ダメージくらった。"
  },
  {
    "message": "珍念は血の気を引かせ。"
  },
  {
    "message": "朽ちた枯れ木のようにヘタり込む。"
  },
  {
    "name": "珍念",
    "message": "ボ、ボクはチキン野郎じゃない。"
  },
  {
    "name": "横山",
    "message": "…女性だけ残して退去する気はございません。"
  },
  {
    "name": "珍念",
    "message": "ちくしょおおおっ、お、覚えてろぉぉっ！"
  },
  {
    "message": "珍念の精神力は残り０だ！"
  },
  {
    "message": "珍念は這々の体で逃げ出した！"
  },
  {
    "name": "横山",
    "message": "ふっ…。"
  },
  {
    "name": "雪菜",
    "message": "す、凄いです。"
  },
  {
    "name": "横山",
    "message": "色々と情報が手に入りました。"
  },
  {
    "message": "横山サンは頑張った！"
  },
  {
    "message": "横山サンのレベルが上がった！"
  },
  {
    "message": "横山サンは「口先攻撃」を覚えた！"
  },
  {
    "name": "横山",
    "message": "先を急ぎましょう。"
  },
  {
    "name": "咲美",
    "message": "う、うん。"
  },
  {
    "name": "横山",
    "message": "少し遠回りになりますが、こちらから迂回すれば、部屋に戻れるはずです。"
  },
  {
    "name": "雪菜",
    "message": "っ、わかりました。"
  },
  {
    "name": "彦麻呂",
    "message": "…。"
  },
  {
    "name": "咲美",
    "message": "行こ。"
  },
  {
    "name": "彦麻呂",
    "message": "ですね。"
  },
  {
    "name": "咲美",
    "message": "…どしたの？"
  },
  {
    "name": "彦麻呂",
    "message": "嫉妬しちゃいましたぁ。"
  },
  {
    "name": "咲美",
    "message": "嫉妬？"
  },
  {
    "name": "彦麻呂",
    "message": "横山サンってデキる方なんですねぇ。"
  },
  {
    "name": "咲美",
    "message": "仲間として頼もしいな。"
  },
  {
    "name": "彦麻呂",
    "message": "それに比べて私は…。"
  },
  {
    "name": "咲美",
    "message": "センセーだって頑張ってた。"
  },
  {
    "name": "彦麻呂",
    "message": "…そうでしょうかぁ。"
  },
  {
    "name": "咲美",
    "message": "私はちゃんと見てるよ。"
  },
  {
    "name": "彦麻呂",
    "message": "何だか立場がないですぅ。"
  },
  {
    "name": "咲美",
    "message": "いいから、行こ。"
  },
  {
    "name": "彦麻呂",
    "message": "…。"
  },
  {
    "name": "咲美",
    "message": "私達は４人で一つのチームだろ？"
  },
  {
    "message": "彼女は麻呂の肩をポンポンと叩き。"
  },
  {
    "message": "そのまま優しく手を引いてくれた。"
  },
  {
    "message": "奥さんの手はいつだって温かく。"
  },
  {
    "message": "麻呂の事を元気づけてくれるでおじゃる。"
  },
  {
    "message": "ブタ男３は咲美に一目惚れした！"
  },
  {
    "name": "咲美",
    "message": "う、うわっ…。"
  },
  {
    "message": "ブタ男３の特殊攻撃！"
  },
  {
    "message": "ブタ男３は咲美を追い回した！"
  },
  {
    "message": "必死に逃げる咲美。"
  },
  {
    "message": "でもブタ男３は諦めない。"
  },
  {
    "message": "それを見たブタ男４も、咲美に一目惚れした！"
  },
  {
    "name": "咲美",
    "message": "！？"
  },
  {
    "message": "ブタ男４が共闘。"
  },
  {
    "message": "咲美の前に立ちはだかる！"
  },
  {
    "message": "咲美はどこにも逃げられない！"
  },
  {
    "message": "ガバッ。"
  },
  {
    "name": "咲美",
    "message": "わわわっ！"
  },
  {
    "message": "ブタ男３は咲美の胸元をはだけた！"
  },
  {
    "message": "痛恨の羞恥プレイ！"
  },
  {
    "message": "咲美は４０のダメージを受けた！"
  },
  {
    "message": "ブタ男３は咲美の巨乳に目を奪われてる。"
  },
  {
    "message": "ブタ男４も咲美の巨乳に目を奪われてる。"
  },
  {
    "name": "咲美",
    "message": "テ、テメーらぁ！"
  },
  {
    "message": "咲美は渾身の力で腕を振り解いた！"
  },
  {
    "name": "咲美",
    "message": "はあっ、はあっ…。"
  },
  {
    "name": "彦麻呂",
    "message": "だ、大丈夫ですかぁ？"
  },
  {
    "name": "咲美",
    "message": "っ、大丈夫じゃねーよ。"
  },
  {
    "name": "横山",
    "message": "こいつらは綾瀬さん狙いみたいです。"
  },
  {
    "name": "彦麻呂",
    "message": "…１００年早い事を教えてあげますぅ。"
  },
  {
    "message": "ブタ男３は欲情してる！"
  },
  {
    "message": "さわさわっ。"
  },
  {
    "name": "咲美",
    "message": "き、気安く触ってんじゃねぇ！"
  },
  {
    "name": "咲美",
    "message": "っ、気持ち悪ぃんだよっ！"
  },
  {
    "message": "ブタ男３は咲美の胸を触った！"
  },
  {
    "message": "咲美は２０のダメージを受けた！"
  },
  {
    "message": "咲美は戦闘不能になった。"
  },
  {
    "message": "麻呂達は全滅してしまった！"
  },
  {
    "message": "…ＧＡＭＥ　ＯＶＥＲ…"
  },
  {
    "message": "ブタ男４は欲情してる！"
  },
  {
    "message": "さわさわっ。"
  },
  {
    "name": "咲美",
    "message": "な、何で私ばっかりっ。"
  },
  {
    "name": "咲美",
    "message": "っ、触ンなっ！"
  },
  {
    "message": "ブタ男４は咲美の尻を撫でた！"
  },
  {
    "message": "咲美は２０のダメージを受けた！"
  },
  {
    "message": "咲美は戦闘不能になった。"
  },
  {
    "message": "麻呂達は全滅してしまった！"
  },
  {
    "message": "…ＧＡＭＥ　ＯＶＥＲ…"
  },
  {
    "message": "ブタ男３は雪菜に目をつけた！"
  },
  {
    "message": "さわさわっ。"
  },
  {
    "name": "雪菜",
    "message": "きゃっ！"
  },
  {
    "message": "ブタ男３は雪菜の胸を触った！"
  },
  {
    "message": "雪菜は２５のダメージを受けた！"
  },
  {
    "message": "雪菜は戦闘不能になった。"
  },
  {
    "message": "麻呂達は全滅してしまった！"
  },
  {
    "message": "…ＧＡＭＥ　ＯＶＥＲ…"
  },
  {
    "message": "ブタ男４は股間を勃起させてる！"
  },
  {
    "message": "さわさわっ。"
  },
  {
    "name": "雪菜",
    "message": "さ、触らないでっ！"
  },
  {
    "message": "ブタ男４は雪菜の尻を撫でた！"
  },
  {
    "message": "雪菜は２５のダメージを受けた！"
  },
  {
    "message": "咲美は戦闘不能になった。"
  },
  {
    "message": "麻呂達は全滅してしまった！"
  },
  {
    "message": "…ＧＡＭＥ　ＯＶＥＲ…"
  },
  {
    "name": "ブタ男３",
    "message": "…死ね。"
  },
  {
    "message": "どかっ！"
  },
  {
    "name": "彦麻呂",
    "message": "ひんっ！"
  },
  {
    "message": "ブタ男３は麻呂を蹴った！"
  },
  {
    "message": "麻呂は２５のダメージを受けた！"
  },
  {
    "message": "麻呂は戦闘不能になった。"
  },
  {
    "message": "麻呂達は全滅してしまった！"
  },
  {
    "message": "…ＧＡＭＥ　ＯＶＥＲ…"
  },
  {
    "name": "ブタ男４",
    "message": "…男は消えろ。"
  },
  {
    "message": "どかっ！"
  },
  {
    "name": "彦麻呂",
    "message": "ぐはっ！"
  },
  {
    "message": "ブタ男４は麻呂を蹴った！"
  },
  {
    "message": "麻呂は２５のダメージを受けた！"
  },
  {
    "message": "麻呂は戦闘不能になった。"
  },
  {
    "message": "麻呂達は全滅してしまった！"
  },
  {
    "message": "…ＧＡＭＥ　ＯＶＥＲ…"
  },
  {
    "name": "ブタ男３",
    "message": "…死ね。"
  },
  {
    "message": "どかっ！"
  },
  {
    "name": "横山",
    "message": "くっ…。"
  },
  {
    "message": "ブタ男３は横山を蹴った！"
  },
  {
    "message": "横山は２５のダメージを受けた！"
  },
  {
    "message": "横山は戦闘不能になった。"
  },
  {
    "message": "麻呂達は全滅してしまった！"
  },
  {
    "message": "…ＧＡＭＥ　ＯＶＥＲ…"
  },
  {
    "name": "ブタ男４",
    "message": "…男は消えろ。"
  },
  {
    "message": "どかっ！"
  },
  {
    "name": "横山",
    "message": "くっ…。"
  },
  {
    "message": "ブタ男４は横山を蹴った！"
  },
  {
    "message": "横山は２５のダメージを受けた！"
  },
  {
    "message": "横山は戦闘不能になった。"
  },
  {
    "message": "麻呂達は全滅してしまった！"
  },
  {
    "message": "…ＧＡＭＥ　ＯＶＥＲ…"
  },
  {
    "name": "ブタ男３",
    "message": "…野郎共の駆逐完了。"
  },
  {
    "message": "ブタ男は舌なめずりし。"
  },
  {
    "message": "咲美のオッパイを視姦してる。"
  },
  {
    "message": "雪菜のオッパイを視姦してる。"
  },
  {
    "name": "ブタ男４",
    "message": "…野郎共の駆逐完了。"
  },
  {
    "message": "ブタ男は舌なめずりし。"
  },
  {
    "message": "咲美のオッパイを視姦してる。"
  },
  {
    "message": "雪菜のオッパイを視姦してる。"
  },
  {
    "name": "横山",
    "message": "うぐっ…。"
  },
  {
    "name": "雪菜",
    "message": "だ、大丈夫ですか？"
  },
  {
    "message": "雪菜が横山サンに駆け寄り。"
  },
  {
    "message": "後ろからギュッと抱き締める。"
  },
  {
    "name": "雪菜",
    "message": "っ、負けないで。"
  },
  {
    "name": "横山",
    "message": "も、もちろんですとも。"
  },
  {
    "message": "雪菜に癒され。"
  },
  {
    "message": "横山の体力が３０回復した。"
  },
  {
    "message": "横山の体力は残り"
  },
  {
    "message": "になった。"
  },
  {
    "name": "横山",
    "message": "うぐっ…。"
  },
  {
    "name": "雪菜",
    "message": "ま、任せて下さいっ。"
  },
  {
    "message": "再び横山サンに駆け寄ろうとする雪菜。"
  },
  {
    "message": "しかしブタ男が行く手を阻み。"
  },
  {
    "message": "彼女は横山サンを癒す事ができない。"
  },
  {
    "name": "咲美",
    "message": "こ、心が折れそうだぁ。"
  },
  {
    "name": "雪菜",
    "message": "っ、しっかり。"
  },
  {
    "message": "雪菜が咲美に駆け寄り。"
  },
  {
    "message": "両手をギュッと握って励ます。"
  },
  {
    "name": "雪菜",
    "message": "こんなブタさんに負ける綾瀬さんじゃありません。"
  },
  {
    "name": "咲美",
    "message": "っ…。"
  },
  {
    "message": "雪菜に励まされ。"
  },
  {
    "message": "咲美の体力が３０回復した。"
  },
  {
    "message": "咲美の体力は残り"
  },
  {
    "message": "になった。"
  },
  {
    "name": "咲美",
    "message": "ヤ、ヤバ…っ。"
  },
  {
    "name": "雪菜",
    "message": "あ、綾瀬さんっ？"
  },
  {
    "message": "再び咲美に駆け寄ろうとする雪菜。"
  },
  {
    "message": "しかしブタ男が行く手を阻み。"
  },
  {
    "message": "彼女は咲美を励ます事ができない。"
  },
  {
    "name": "彦麻呂",
    "message": "キ、キツいですねぇ。"
  },
  {
    "name": "雪菜",
    "message": "っ、先生。"
  },
  {
    "message": "雪菜が麻呂に駆け寄り。"
  },
  {
    "message": "後ろからギュッと抱き締める。"
  },
  {
    "name": "雪菜",
    "message": "元気を出して下さい。"
  },
  {
    "name": "彦麻呂",
    "message": "オ、オッパイパワーを頂きましたぁ。"
  },
  {
    "message": "雪菜に励まされ。"
  },
  {
    "message": "麻呂の体力が３０回復した。"
  },
  {
    "message": "麻呂の体力は残り"
  },
  {
    "message": "になった。"
  },
  {
    "name": "雅史",
    "message": "ぐはぁ…っ。"
  },
  {
    "name": "雪菜",
    "message": "せ、先生っ。"
  },
  {
    "message": "再び麻呂に駆け寄ろうとする雪菜。"
  },
  {
    "message": "しかしブタ男が行く手を阻み。"
  },
  {
    "message": "彼女は麻呂を励ます事ができない。"
  },
  {
    "message": "誰が攻撃しますか？"
  }
]